LICENSE
README.md
pyproject.toml
setup.cfg
src/legacy_quadpy.egg-info/PKG-INFO
src/legacy_quadpy.egg-info/SOURCES.txt
src/legacy_quadpy.egg-info/dependency_links.txt
src/legacy_quadpy.egg-info/entry_points.txt
src/legacy_quadpy.egg-info/requires.txt
src/legacy_quadpy.egg-info/top_level.txt
src/ndim/__about__.py
src/ndim/__init__.py
src/ndim/enr.py
src/ndim/enr2.py
src/ndim/nball.py
src/ndim/ncube.py
src/ndim/nsimplex.py
src/ndim/nsphere.py
src/orthopy/__init__.py
src/orthopy/helpers.py
src/orthopy/c1/__init__.py
src/orthopy/c1/associated_legendre.py
src/orthopy/c1/chebyshev1.py
src/orthopy/c1/chebyshev2.py
src/orthopy/c1/gegenbauer.py
src/orthopy/c1/jacobi.py
src/orthopy/c1/legendre.py
src/orthopy/c1/tools.py
src/orthopy/cn/__init__.py
src/orthopy/cn/main.py
src/orthopy/cn/tools.py
src/orthopy/e1r/__init__.py
src/orthopy/e1r/main.py
src/orthopy/e1r/tools.py
src/orthopy/e1r2/__init__.py
src/orthopy/e1r2/main.py
src/orthopy/e1r2/tools.py
src/orthopy/enr2/__init__.py
src/orthopy/enr2/main.py
src/orthopy/enr2/tools.py
src/orthopy/s2/__init__.py
src/orthopy/s2/tools.py
src/orthopy/s2/xu.py
src/orthopy/s2/zernike.py
src/orthopy/s2/zernike2.py
src/orthopy/t2/__init__.py
src/orthopy/t2/main.py
src/orthopy/t2/tools.py
src/orthopy/tools/__init__.py
src/orthopy/tools/generate_rc.py
src/orthopy/u3/__init__.py
src/orthopy/u3/main.py
src/orthopy/u3/tools.py
src/quadpy/__about__.py
src/quadpy/__init__.py
src/quadpy/_cli.py
src/quadpy/_exception.py
src/quadpy/_optimize.py
src/quadpy/_scipy_compat.py
src/quadpy/c1/__init__.py
src/quadpy/c1/_adaptive.py
src/quadpy/c1/_chebyshev_gauss.py
src/quadpy/c1/_clenshaw_curtis.py
src/quadpy/c1/_fejer.py
src/quadpy/c1/_gauss_jacobi.py
src/quadpy/c1/_gauss_kronrod.py
src/quadpy/c1/_gauss_legendre.py
src/quadpy/c1/_gauss_lobatto.py
src/quadpy/c1/_gauss_patterson.py
src/quadpy/c1/_gauss_radau.py
src/quadpy/c1/_helpers.py
src/quadpy/c1/_midpoint.py
src/quadpy/c1/_newton_cotes.py
src/quadpy/c1/_trapezoidal.py
src/quadpy/c2/__init__.py
src/quadpy/c2/_albrecht_collatz.py
src/quadpy/c2/_burnside.py
src/quadpy/c2/_cohen_gismalla.py
src/quadpy/c2/_franke.py
src/quadpy/c2/_hammer_stroud.py
src/quadpy/c2/_helpers.py
src/quadpy/c2/_irwin.py
src/quadpy/c2/_maxwell.py
src/quadpy/c2/_meister.py
