Metadata-Version: 2.1
Name: legacy-quadpy
Version: 0.16.10
Summary: Numerical integration, quadrature for various domains
Home-page: https://github.com/zfergus/legacy-quadpy
Author: Nico Schlömer
Author-email: nico.schloemer@gmail.com
License: GPL-3.0-or-later
Project-URL: Code, https://github.com/zfergus/legacy-quadpy
Project-URL: Issues, https://github.com/zfergus/legacy-quadpy/issues
Project-URL: Funding, https://github.com/sponsors/nschloe
Keywords: mathematics,physics,engineering,quadrature,cubature,integration,numerical integration
Classifier: Development Status :: 4 - Beta
Classifier: Intended Audience :: Science/Research
Classifier: License :: OSI Approved :: GNU General Public License v3 or later (GPLv3+)
Classifier: Operating System :: OS Independent
Classifier: Programming Language :: Python
Classifier: Programming Language :: Python :: 3
Classifier: Programming Language :: Python :: 3.7
Classifier: Programming Language :: Python :: 3.8
Classifier: Programming Language :: Python :: 3.9
Classifier: Programming Language :: Python :: 3.10
Classifier: Topic :: Scientific/Engineering
Classifier: Topic :: Scientific/Engineering :: Mathematics
Requires-Python: >=3.7
License-File: LICENSE
Requires-Dist: importlib_metadata; python_version < "3.8"
Requires-Dist: numpy
Requires-Dist: scipy
Requires-Dist: sympy
Provides-Extra: all
Requires-Dist: matplotlib; extra == "all"
Requires-Dist: vtk; extra == "all"
Provides-Extra: plot
Requires-Dist: matplotlib; extra == "plot"
Requires-Dist: vtk; extra == "plot"
